{


    "carbook":[{
        "name": "LAkki",
        "car": "name",
        "city": "bhopal",
        "p": 10000000,
        "color":"red"  


    },{
        "name": "rohit",
        "car": "name",
        "city": "indore",
        "p": 10000000,
        "color":"red"   
    },{
         "name": "adi",
        "car": "name",
        "city": "shihore",
        "p": 10000000 ,
        "color":"red"  
    },{
        "name": "rajesh",
        "car": "name",
        "city": "betul",
        "p": 10000000 ,
        "color":"red"  
    }]
}